codeaj/__init__.py
codeaj/scrap.py
codeaj-0.0.2.dist-info/LICENSE.txt
codeaj-0.0.2.dist-info/METADATA
codeaj-0.0.2.dist-info/WHEEL
codeaj-0.0.2.dist-info/top_level.txt
codeaj-0.0.2.dist-info/RECORD
