Metadata-Version: 2.1
Name: codeaj
Version: 0.0.2
Summary: scrap all the data from the website and convert it into requried language
Home-page: UNKNOWN
Author: ajay pandit
Author-email: <ajayoneness123@gmail.com>
License: UNKNOWN
Keywords: python,scrap,googe translate
Platform: UNKNOWN
Classifier: Development Status :: 1 - Planning
Classifier: Intended Audience :: Developers
Classifier: Programming Language :: Python :: 3
Classifier: Operating System :: Unix
Classifier: Operating System :: MacOS :: MacOS X
Classifier: Operating System :: Microsoft :: Windows
Requires-Dist: requests
Requires-Dist: bs4
Requires-Dist: google-trans-new
